jsoncodable/__init__.py
jsoncodable/jsoncodable.py
to_dict-0.0.7.dist-info/LICENSE
to_dict-0.0.7.dist-info/METADATA
to_dict-0.0.7.dist-info/WHEEL
to_dict-0.0.7.dist-info/top_level.txt
to_dict-0.0.7.dist-info/RECORD
