Metadata-Version: 2.1
Name: to-dict
Version: 0.0.7
Summary: to_dict
Home-page: https://github.com/kkristof200/py_todict
Author: Kristof
License: UNKNOWN
Platform: UNKNOWN
Classifier: Programming Language :: Python :: 3
Classifier: License :: OSI Approved :: MIT License
Classifier: Operating System :: OS Independent
Requires-Python: >=3.5
